{
  "$schema": "http://json-schema.org/draft-07/schema#",
  "title": "Transaction",
  "description": "Represents a financial transaction record, encompassing invoices, payments, receipts, journals, orders, and quotes. Internal Name: Transaction (file_num: 5).",
  "type": "object",
  "properties": {
    "SequenceNumber": {
      "type": "integer",
      "description": "Internal unique identifier for the transaction record. Indexed."
    },
    "LastModifiedTime": {
      "type": "string",
      "format": "date-time",
      "description": "Timestamp indicating the last time the transaction record was modified."
    },
    "OurRef": {
      "type": "string",
      "maxLength": 12,
      "description": "Internal reference number (e.g., invoice number, cheque number, receipt number, journal number). Indexed. (Mutable: conditionally)"
    },
    "TransDate": {
      "type": "string",
      "format": "date",
      "description": "The primary date associated with the transaction (e.g., invoice date, payment date). Indexed. (Mutable: conditionally)"
    },
    "EnterDate": {
      "type": "string",
      "format": "date",
      "description": "The date the transaction was entered into the system. Indexed."
    },
    "DueDate": {
      "type": "string",
      "format": "date",
      "description": "The date payment is due for invoices. (Mutable: conditionally)"
    },
    "Period": {
      "type": "integer",
      "description": "The accounting period to which the transaction is assigned. Indexed."
    },
    "Type": {
      "type": "string",
      "maxLength": 4,
      "description": "The type of the transaction. Determines its accounting behaviour. Indexed.",
      "enum": [
        "CP",
        "CR",
        "DI",
        "CI",
        "JN",
        "SO",
        "PO",
        "QU",
        "SOC",
        "SOI",
        "POC",
        "POI",
        "CPC",
        "CPD",
        "CRC",
        "CRD",
        "DIC",
        "DII",
        "CIC",
        "CII",
        "JNS",
        "JNB",
        "JNW",
        "JNC",
        "JNT",
        "JNV"
      ],
      "enumDescriptions": {
        "CP": "Cash Payment/Purchase",
        "CR": "Cash Receipt/Sale",
        "DI": "Debtor Invoice (Sales Invoice)",
        "CI": "Creditor Invoice (Purchase Invoice)",
        "JN": "General Journal",
        "SO": "Sales Order",
        "PO": "Purchase Order",
        "QU": "Quote",
        "SOC": "Sales Order - Complete (Sold)",
        "SOI": "Sales Order - Incomplete",
        "POC": "Purchase Order - Complete (Bought)",
        "POI": "Purchase Order - Incomplete",
        "CPC": "Cash Payment for Creditor Invoice",
        "CPD": "Returned Refund to Debtor",
        "CRC": "Received Refund from Creditor",
        "CRD": "Receipt for Debtor Invoice",
        "DIC": "Debtor Invoice - Fully Paid",
        "DII": "Debtor Invoice - Incomplete/Unpaid",
        "CIC": "Creditor Invoice - Fully Paid",
        "CII": "Creditor Invoice - Incomplete/Unpaid",
        "JNS": "Stock Journal",
        "JNB": "Banking Journal",
        "JNW": "Write-off Journal (Internal)",
        "JNC": "Contra Journal (Internal)",
        "JNT": "Stock Transfer Journal",
        "JNV": "Stock Revaluation Journal (Internal)"
      }
    },
    "TheirRef": {
      "type": "string",
      "maxLength": 32,
      "description": "The reference number provided by the other party (e.g., supplier's invoice number, customer's PO number). (Mutable: freely, script-only)"
    },
    "NameCode": {
      "type": "string",
      "maxLength": 12,
      "description": "The code linking this transaction to a customer, supplier, or other contact in the Name table. Indexed."
    },
    "Flag": {
      "type": "string",
      "maxLength": 6,
      "description": "A user-defined flag for categorization or marking. Non-empty value displays a flag icon in lists. (Mutable: freely, script-only)"
    },
    "Description": {
      "type": "string",
      "maxLength": 1024,
      "description": "A detailed description of the transaction purpose or content. (Mutable: conditionally)"
    },
    "Gross": {
      "type": "number",
      "description": "The total gross amount of the transaction (tax inclusive)."
    },
    "Analysis": {
      "type": "string",
      "maxLength": 10,
      "description": "A user-defined code for analysis, reporting, or grouping (e.g., batch number, department, project). (Mutable: freely, script-only)"
    },
    "Contra": {
      "type": "string",
      "maxLength": 8,
      "description": "The primary balancing account code (e.g., Bank account for payments/receipts, Accounts Payable/Receivable for invoices)."
    },
    "ToFrom": {
      "type": "string",
      "maxLength": 256,
      "description": "The name of the party the transaction is to or from (e.g., Payee, Payer). Often populated from the linked Name record. (Mutable: conditionally)"
    },
    "Status": {
      "type": "string",
      "maxLength": 2,
      "description": "Indicates whether the transaction has been posted to the ledger. Indexed.",
      "enum": ["U", "P"],
      "enumDescriptions": {
        "U": "Unposted",
        "P": "Posted"
      }
    },
    "Hold": {
      "type": "boolean",
      "description": "If true, the transaction cannot be posted. (Mutable: conditionally)"
    },
    "DatePaid": {
      "type": ["string", "null"],
      "format": "date",
      "description": "For invoices, the date the last payment was received/made."
    },
    "AmtPaid": {
      "type": "number",
      "description": "For invoices, the total amount paid against this invoice to date."
    },
    "PayAmount": {
      "type": "number",
      "description": "For creditor payments, the amount allocated to be paid in the next payment run."
    },
    "Aging": {
      "type": "integer",
      "description": "The aging cycle number when this transaction was last aged (relevant for open-item statements)."
    },
    "TaxAmount": {
      "type": "number",
      "description": "The total tax amount calculated for the transaction."
    },
    "TaxCycle": {
      "type": "integer",
      "description": "The GST/VAT/Tax reporting cycle number in which this transaction was finalized."
    },
    "Recurring": {
      "type": "boolean",
      "description": "Flag indicating if this is a recurring transaction template."
    },
    "Printed": {
      "type": "integer",
      "description": "Status indicating if the transaction form (invoice, cheque, etc.) has been printed (0=No, 1=Yes). (Mutable: freely, script-only)"
    },
    "Flags": {
      "type": "integer",
      "description": "A bitmask field storing various boolean settings/attributes for the transaction (e.g., Was Cancelled, Is Job Invoice)."
    },
    "TaxProcessed": {
      "type": "number",
      "description": "Internal field related to tax processing."
    },
    "Salesperson": {
      "type": "string",
      "maxLength": 6,
      "description": "The code of the salesperson associated with this transaction. Can be used for reporting or departmental allocation. (Mutable: conditionally)"
    },
    "Colour": {
      "type": "integer",
      "minimum": 0,
      "maximum": 7,
      "description": "A user-assigned colour index (0-7) for visual identification in lists. Labels are user-defined in preferences. (Mutable: conditionally)"
    },
    "BankJNSeq": {
      "type": ["integer", "null"],
      "description": "The sequence number of the Banking Journal transaction if this receipt was banked using the Banking command."
    },
    "PaymentMethod": {
      "type": "integer",
      "description": "Indicates the method of payment or receipt.",
      "enum": [0, 1, 2, 3, 4, 5, 6, 7],
      "enumDescriptions": {
        "0": "None/Unspecified",
        "1": "Cash",
        "2": "Cheque",
        "3": "Electronic/Direct Credit",
        "4": "Credit Card",
        "5": "User Defined 1",
        "6": "User Defined 2",
        "7": "User Defined 3"
      }
    },
    "TimePosted": {
      "type": ["string", "null"],
      "format": "date-time",
      "description": "Timestamp indicating when the transaction was posted."
    },
    "SecurityLevel": {
      "type": "integer",
      "description": "The highest security level assigned to any of the detail lines in this transaction. Indexed."
    },
    "User1": {
      "type": "string",
      "maxLength": 256,
      "description": "User-defined text field 1. (Mutable: freely, script-only)"
    },
    "User2": {
      "type": "string",
      "maxLength": 256,
      "description": "User-defined text field 2. (Mutable: freely, script-only)"
    },
    "User3": {
      "type": "string",
      "maxLength": 256,
      "description": "User-defined text field 3. (Mutable: freely, script-only)"
    },
    "PromptPaymentDate": {
      "type": ["string", "null"],
      "format": "date",
      "description": "The date by which payment must be made to receive a prompt payment discount. (Mutable: freely, script-only)"
    },
    "PromptPaymentAmt": {
      "type": "number",
      "description": "The calculated amount of the prompt payment discount available."
    },
    "ProdPriceCode": {
      "type": "string",
      "maxLength": 2,
      "description": "The product pricing level (A-F) applied to this transaction.",
      "enum": ["A", "B", "C", "D", "E", "F", ""],
      "enumDescriptions": {
        "A": "Price Level A",
        "B": "Price Level B",
        "C": "Price Level C",
        "D": "Price Level D",
        "E": "Price Level E",
        "F": "Price Level F",
        "": "Default/Not Specified"
      }
    },
    "MailingAddress": {
      "type": "string",
      "maxLength": 256,
      "description": "The specific mailing address used for this transaction, overriding the default from the Name record if necessary. (Mutable: conditionally)"
    },
    "DeliveryAddress": {
      "type": "string",
      "maxLength": 256,
      "description": "The specific delivery address used for this transaction, overriding the default from the Name record if necessary. (Mutable: conditionally)"
    },
    "FreightCode": {
      "type": "string",
      "maxLength": 32,
      "description": "The product code used for freight charges on this order/invoice."
    },
    "FreightAmount": {
      "type": "number",
      "description": "The amount charged for freight on this order/invoice."
    },
    "FreightDetails": {
      "type": "string",
      "maxLength": 256,
      "description": "Additional details regarding the freight charges. (Mutable: freely, script-only)"
    },
    "SpecialBank": {
      "type": "string",
      "maxLength": 32,
      "description": "Special bank identifier, potentially used for specific payment types or integrations. (Mutable: freely, script-only)"
    },
    "SpecialBranch": {
      "type": "string",
      "maxLength": 32,
      "description": "Special bank branch identifier. (Mutable: freely, script-only)"
    },
    "SpecialAccount": {
      "type": "string",
      "maxLength": 32,
      "description": "Special bank account identifier. (Mutable: freely, script-only)"
    },
    "Currency": {
      "type": "string",
      "maxLength": 4,
      "description": "The currency code for the transaction (e.g., 'USD', 'EUR'). Empty for base currency."
    },
    "ExchangeRate": {
      "type": "number",
      "description": "The exchange rate applied to this foreign currency transaction. 0 for base currency."
    },
    "EnteredBy": {
      "type": "string",
      "maxLength": 4,
      "description": "The initials of the user who originally entered the transaction."
    },
    "PostedBy": {
      "type": "string",
      "maxLength": 4,
      "description": "The initials of the user who posted the transaction."
    },
    "AmtWrittenOff": {
      "type": "number",
      "description": "The amount of this invoice that has been written off."
    },
    "OrderTotal": {
      "type": "number",
      "description": "The total value of the associated order (for invoices generated from orders)."
    },
    "OrderShipped": {
      "type": "number",
      "description": "The value of goods shipped on the associated order."
    },
    "OrderDeposit": {
      "type": "number",
      "description": "The amount of deposit recorded against the associated order."
    },
    "OriginatingOrderSeq": {
      "type": ["integer", "null"],
      "description": "The SequenceNumber of the Sales Order or Purchase Order from which this invoice was generated."
    },
    "CurrencyTransferSeq": {
      "type": ["integer", "null"],
      "description": "The SequenceNumber of the related transaction in a currency transfer pair."
    },
    "PromptPaymentTerms": {
      "type": "integer",
      "description": "The specific prompt payment terms code applied to this transaction (overriding Name record)."
    },
    "PromptPaymentDisc": {
      "type": "number",
      "description": "The specific prompt payment discount percentage applied to this transaction."
    },
    "ApprovedBy1": {
      "type": "string",
      "maxLength": 4,
      "description": "Initials of the first user who approved this transaction (if approval workflow is used). (Mutable: conditionally, script-only)"
    },
    "ApprovedBy2": {
      "type": "string",
      "maxLength": 4,
      "description": "Initials of the second user who approved this transaction (if approval workflow is used). (Mutable: conditionally, script-only)"
    },
    "UserNum": {
      "type": "number",
      "description": "A user-defined number field for custom data storage, often used by scripts. (Mutable: freely, script-only)"
    },
    "UserText": {
      "type": "string",
      "maxLength": 256,
      "description": "A user-defined text field for custom data storage, often used by scripts. (Mutable: freely, script-only)"
    },
    "User4": {
      "type": "string",
      "maxLength": 16,
      "description": "User-defined text field 4. (Mutable: freely, script-only)"
    },
    "User5": {
      "type": "string",
      "maxLength": 16,
      "description": "User-defined text field 5. (Mutable: freely, script-only)"
    },
    "User6": {
      "type": "string",
      "maxLength": 16,
      "description": "User-defined text field 6. (Mutable: freely, script-only)"
    },
    "User7": {
      "type": "string",
      "maxLength": 16,
      "description": "User-defined text field 7. (Mutable: freely, script-only)"
    },
    "User8": {
      "type": "string",
      "maxLength": 16,
      "description": "User-defined text field 8. (Mutable: freely, script-only)"
    },
    "TaggedText": {
      "type": "string",
      "maxLength": 256,
      "description": "Stores key-value pairs for custom data, primarily accessed via scripting functions GetTaggedValue/SetTaggedValue. (Mutable: freely, script-only)"
    },
    "Emailed": {
      "type": "integer",
      "description": "Status indicating if the transaction form has been emailed (0=No, 1=Yes). (Mutable: freely, script-only)"
    },
    "Transferred": {
      "type": "integer",
      "description": "Status related to electronic transfer (e.g., eInvoicing sent status). (Mutable: freely, script-only)"
    }
  },
  "required": ["SequenceNumber", "LastModifiedTime", "TransDate", "Type"]
}
